[{"model": "puntos.canalacupuntura", "pk": 1, "fields": {"cvecanal": "1", "nomcanal": "canal1", "bandactivo": true, "datelastupdate": "2023-04-14T17:45:35.870Z"}}, {"model": "puntos.canalacupuntura", "pk": 2, "fields": {"cvecanal": "2", "nomcanal": "canal2", "bandactivo": true, "datelastupdate": "2023-04-14T17:45:59.958Z"}}, {"model": "puntos.canalacupuntura", "pk": 3, "fields": {"cvecanal": "3", "nomcanal": "canal3", "bandactivo": true, "datelastupdate": "2023-04-14T17:49:29.144Z"}}, {"model": "puntos.canalacupuntura", "pk": 4, "fields": {"cvecanal": "4", "nomcanal": "canal4", "bandactivo": true, "datelastupdate": "2023-04-14T17:54:54.586Z"}}, {"model": "puntos.enfermedad", "pk": 1, "fields": {"cveenfermedad": "1", "nomenfermedad": "Enfermedad1", "bandactivo": true, "datelastupdate": "2023-05-02T17:46:28Z"}}, {"model": "puntos.puntoacupuntura", "pk": 1, "fields": {"cvepunto": "1", "nompunto": "punto1", "nomlargopunto": "El punto uno", "cvecanal": 1, "bandactivo": true, "datelastupdate": "2023-04-14T19:53:52.542Z"}}, {"model": "puntos.puntoacupuntura", "pk": 2, "fields": {"cvepunto": "punto2", "nompunto": "punto2", "nomlargopunto": "punto2", "cvecanal": 2, "bandactivo": true, "datelastupdate": "2023-05-04T01:54:37.750Z"}}, {"model": "puntos.puntocaracteristicas", "pk": 1, "fields": {"cvepunto": 1, "desccaracteristicas": "<h2><strong>Caracteristicas</strong></h2>", "bandactivo": true, "datelastupdate": "2023-05-02T23:47:01.826Z"}}, {"model": "puntos.puntodocumentos", "pk": 4, "fields": {"cvepunto": 1, "ligadocumento": "documentos_puntos/readme.html", "bandactivo": true, "datelastupdate": "2023-06-24T20:34:46.015Z"}}, {"model": "puntos.puntoenfermedad", "pk": 1, "fields": {"cvepunto": 1, "cveenfermedad": 1, "bandactivo": true, "datelastupdate": "2023-05-03T19:11:27.742Z"}}, {"model": "puntos.puntoimagenes", "pk": 1, "fields": {"cvepunto": 1, "ligaimagen": "images_puntos/Captura_desde_2023-05-16_18-04-53.png", "bandactivo": true, "datelastupdate": "2023-05-03T19:11:27.742Z"}}, {"model": "puntos.puntoimagenes", "pk": 7, "fields": {"cvepunto": 1, "ligaimagen": "images_puntos/Captura_desde_2023-06-11_19-32-49_TOZH2yk.png", "bandactivo": true, "datelastupdate": "2023-06-23T23:06:41.805Z"}}, {"model": "puntos.puntoimagenlocalizacion", "pk": 1, "fields": {"cvepunto": 1, "ligaimagen": "imagen2", "bandactivo": true, "datelastupdate": "2023-05-03T19:11:27.742Z"}}, {"model": "puntos.puntolocalizacion", "pk": 1, "fields": {"cvepunto": 1, "desclocalizacion": "21342", "bandactivo": true, "datelastupdate": "2023-05-03T19:11:27.742Z"}}, {"model": "puntos.puntosignificado", "pk": 1, "fields": {"cvepunto": 1, "descsignificado": "<h1><strong>significado punto12</strong></h1>", "bandactivo": true, "datelastupdate": "2023-04-24T19:23:29Z"}}, {"model": "puntos.puntovideos", "pk": 1, "fields": {"cvepunto": 1, "ligavideo": "HUXG5AdAqmI", "bandactivo": true, "datelastupdate": "2023-06-23T23:04:43.871Z"}}, {"model": "puntos.puntovideos", "pk": 2, "fields": {"cvepunto": 1, "ligavideo": "nFRwKivq9Qo", "bandactivo": true, "datelastupdate": "2023-06-23T23:04:43.871Z"}}, {"model": "puntos.puntovideos", "pk": 3, "fields": {"cvepunto": 1, "ligavideo": "N2SBZWs-L4w", "bandactivo": true, "datelastupdate": "2023-06-23T23:04:43.871Z"}}]